setup.cfg
setup.py
nnsearch/__init__.py
nnsearch/baseindex.py
nnsearch/distances.py
nnsearch/flannindex.py
nnsearch.egg-info/PKG-INFO
nnsearch.egg-info/SOURCES.txt
nnsearch.egg-info/dependency_links.txt
nnsearch.egg-info/requires.txt
nnsearch.egg-info/top_level.txt
nnsearch/algos/BoundaryForest.py
nnsearch/algos/__init__.py
nnsearch/algos/pmtree.py
nnsearch/algos/rstartree.py
nnsearch/algos/rtree.py
nnsearch/algos/utils/__init__.py
nnsearch/algos/utils/entry.py
nnsearch/algos/utils/nodes.py
nnsearch/algos/utils/rectangle.py
nnsearch/approx/Annoy.py
nnsearch/approx/BF.py
nnsearch/approx/FlannAuto.py
nnsearch/approx/KMeans.py
nnsearch/approx/LSHFlann.py
nnsearch/approx/LSHNearPy.py
nnsearch/approx/RKDTree.py
nnsearch/approx/__init__.py
nnsearch/datasets/__init__.py
nnsearch/datasets/datasets.py
nnsearch/datasets/density.py
nnsearch/datasets/sample/circle_10d_100000.npy
nnsearch/datasets/sample/circle_10d_100000_old.npy
nnsearch/datasets/sample/circle_2d_100000.npy
nnsearch/datasets/sample/circle_3d_100000.npy
nnsearch/datasets/sample/circle_5d_100000.npy
nnsearch/datasets/sample/clusters_2d_10c_100000.npy
nnsearch/datasets/sample/clusters_3d_10c_100000.npy
nnsearch/datasets/sample/dim1000_10000.npy
nnsearch/datasets/sample/elipse10_04_2d_100000.npy
nnsearch/datasets/sample/elipse_3d_144_414_441_100000.npy
nnsearch/datasets/sample/german_post_codes.npy
nnsearch/datasets/sample/uniform_1d_100000.npy
nnsearch/exact/BallTreeScikit.py
nnsearch/exact/BruteFlann.py
nnsearch/exact/KDFlann.py
nnsearch/exact/KDTreeScikit.py
nnsearch/exact/PMTree.py
nnsearch/exact/RSTreeIndex.py
nnsearch/exact/RTreeIndex.py
nnsearch/exact/__init__.py