Metadata-Version: 1.0
Name: nnsearch
Version: 0.1
Summary: Exact and approximate nearest neighbors search
Home-page: https://github.com/pkariz/nnsearch
Author: Primoz Kariz
Author-email: vegycslol@gmail.com
License: GNU GPLv3
Platform: UNKNOWN
